neuralkernel/__init__.py
neuralkernel/__main__.py
neuralkernel/adjmatrix.py
neuralkernel/constants.py
neuralkernel/graph.py
neuralkernel/networks.py
neuralkernel/neuron.py
neuralkernel/predefined_models.py
neuralkernel/spikekernel.py
neuralkernel/synapse.py
neuralkernel-0.0.8.dist-info/LICENSE
neuralkernel-0.0.8.dist-info/METADATA
neuralkernel-0.0.8.dist-info/WHEEL
neuralkernel-0.0.8.dist-info/top_level.txt
neuralkernel-0.0.8.dist-info/RECORD
