Metadata-Version: 2.1
Name: neuralkernel
Version: 0.0.8
Summary: neural networks as a general-purpose computational framework
Home-page: UNKNOWN
Author: Noah Stebbins
Author-email: nstebbins1@gmail.com
License: MIT
Platform: UNKNOWN
Classifier: Development Status :: 3 - Alpha
Classifier: Programming Language :: Python :: 3.5
Classifier: Programming Language :: Python :: 3.6
Classifier: Programming Language :: Python :: 3.7
Requires-Dist: numpy
Requires-Dist: matplotlib
Requires-Dist: seaborn
